polars_xml-0.3.1.dist-info/METADATA
polars_xml-0.3.1.dist-info/WHEEL
polars_xml/__init__.py
polars_xml/_typing.py
polars_xml/internal.pyi
polars_xml/polars_xml.abi3.so
polars_xml-0.3.1.dist-info/RECORD
