Metadata-Version: 2.4
Name: polars-xml
Version: 0.3.1
Requires-Dist: polars>=1.32.0
Requires-Python: >=3.10
Project-URL: homepage, https://github.com/mcpar-land/polars-xml
